toquevee/__init__.py
toquevee/err.py
toquevee/filename_to_uuid_preprocessor.py
toquevee/quiver_exporter.py
toquevee/quiver_writer.py
toquevee/toquevee_bundler.py
toquevee-0.1.0.dist-info/METADATA
toquevee-0.1.0.dist-info/RECORD
toquevee-0.1.0.dist-info/WHEEL
toquevee-0.1.0.dist-info/top_level.txt
